Workbook

Sheet 00_Cover
B2: NORTHLINE CONSUMER PRODUCTS
B3: Unit Economics Workbook — SKU contribution, channel view, launch ramp
B4: Fictional CPG portfolio sample · per-unit $ and $000s · formulas only (no VBA)
B6: Purpose
B7: Per-SKU unit P&L (price → contribution), channel mix and contribution, and a 12-month ramp / payback on the launch SKU (NL-Probiotic Bar). Built so FP&A can stress price, COGS, and CAC before a category review.
B9: How to use
B10: 1. Open 01_Assumptions — edit SKU price, COGS, variable selling, slotting, and annual volume (yellow).
B11: 2. Read 02_Unit_P&L — per-unit contribution and contribution margin % by SKU (formulas).
B12: 3. Review 03_Channel_View — mix and channel contribution; fees are yellow inputs.
B13: 4. Stress 04_Cohort_or_Ramp — 12-month volume ramp and cumulative payback on the launch SKU.
B14: 5. Use 05_Dashboard as the one-pager for a category or innovation review.
B16: Color convention
B17: Yellow fill + blue font | C17: =inputs (edit these)
B18: Black font | C18: =formulas (do not overwrite)
B19: Green highlight | C19: =key outputs (contribution, payback)
B21: Tabs
B22: 00_Cover | C22: Purpose and navigation
B23: 01_Assumptions | C23: SKU list, price, COGS, var selling, slotting, volume
B24: 02_Unit_P&L | C24: Per-unit contribution by SKU
B25: 03_Channel_View | C25: Channel mix and contribution
B26: 04_Cohort_or_Ramp | C26: 12-month launch ramp / payback
B27: 05_Dashboard | C27: Dashboard one-pager
B28: 06_Data_Dictionary | C28: Field definitions
B30: Sai Siri Bandaru — Financial Analyst | FP&A | forecasting, variance analysis, Excel
B31: All sample numbers are fictional. No employer data.

Sheet 01_Assumptions
B2: 01 · Assumptions
B3: SKU economics inputs. Yellow = edit. Downstream tabs are formulas.
B5: Company | C5: Northline Consumer Products
B6: Fiscal year | C6: FY26
B7: Currency / units | C7: USD; volume in 000 units; slotting in $000s
B9: SKU | C9: Product | D9: Price $ | E9: COGS $ | F9: Var sell $ | G9: Slotting $000 | H9: Ann vol (000) | I9: Launch? | J9: WACC / hurdle | K9: Notes
B10: NL-CRUNCH | C10: Northline Crunch Bar | D10: 2.49 | E10: 0.92 | F10: 0.18 | G10: 85 | H10: 4200 | I10: N | J10: 0.1 | K10: Core assortment
B11: NL-PROTEIN | C11: Protein Trail Mix | D11: 4.99 | E11: 1.85 | F11: 0.35 | G11: 120 | H11: 2100 | I11: N | J11: =J10 | K11: Core assortment
B12: NL-OAT | C12: Overnight Oats Cup | D12: 3.29 | E12: 1.15 | F12: 0.22 | G12: 95 | H12: 3100 | I12: N | J12: =J10 | K12: Core assortment
B13: NL-KIDS | C13: Kids Fruit Bites | D13: 2.99 | E13: 1.05 | F13: 0.28 | G13: 150 | H13: 2800 | I13: N | J13: =J10 | K13: Core assortment
B14: NL-PROBIO | C14: Probiotic Bar (launch) | D14: 3.79 | E14: 1.42 | F14: 0.4 | G14: 220 | H14: 900 | I14: Y | J14: =J10 | K14: Launch SKU — see ramp tab
B15: NL-COLD | C15: Cold Brew RTD | D15: 2.79 | E15: 0.88 | F15: 0.25 | G15: 110 | H15: 3500 | I15: N | J15: =J10 | K15: Core assortment
B17: Global toggles
B18: Price stress % | C18: 0 | D18: Applied on Unit P&L as Price × (1 + stress)
B19: COGS stress % | C19: 0 | D19: Applied on Unit P&L as COGS × (1 + stress)
B20: Target contribution margin % | C20: 0.35 | D20: Used for RAG on Unit P&L and Dashboard
B21: Payback hurdle (months) | C21: 12 | D21: Launch SKU cumulative contribution vs slotting+CAC
B23: Per-unit $ are shelf / list before channel fees. Slotting is annualized $000s (one-time for launch on ramp tab).

Sheet 02_Unit_P&L
B2: 02 · Unit P&L
B3: Per-unit bridge: stressed price → COGS → var sell → contribution. Annual $000s = unit × volume.
B5: SKU | C5: Product | D5: Price $ | E5: COGS $ | F5: Var sell $ | G5: Unit contrib $ | H5: CM % | I5: vs Target | J5: RAG | K5: Ann vol (000) | L5: Ann contrib $000 | M5: Slotting $000 | N5: Ann CM after slot $000
B6: ='01_Assumptions'!B10 | C6: ='01_Assumptions'!C10 | D6: ='01_Assumptions'!D10*(1+'01_Assumptions'!C18) | E6: ='01_Assumptions'!E10*(1+'01_Assumptions'!C19) | F6: ='01_Assumptions'!F10 | G6: =D6-E6-F6 | H6: =IF(D6=0,0,G6/D6) | I6: =H6-'01_Assumptions'!C20 | J6: =IF(H6>='01_Assumptions'!C20,"Green",IF(H6>='01_Assumptions'!C20-0.05,"Amber","Red")) | K6: ='01_Assumptions'!H10 | L6: =G6*K6 | M6: ='01_Assumptions'!G10 | N6: =L6-M6
B7: ='01_Assumptions'!B11 | C7: ='01_Assumptions'!C11 | D7: ='01_Assumptions'!D11*(1+'01_Assumptions'!C18) | E7: ='01_Assumptions'!E11*(1+'01_Assumptions'!C19) | F7: ='01_Assumptions'!F11 | G7: =D7-E7-F7 | H7: =IF(D7=0,0,G7/D7) | I7: =H7-'01_Assumptions'!C20 | J7: =IF(H7>='01_Assumptions'!C20,"Green",IF(H7>='01_Assumptions'!C20-0.05,"Amber","Red")) | K7: ='01_Assumptions'!H11 | L7: =G7*K7 | M7: ='01_Assumptions'!G11 | N7: =L7-M7
B8: ='01_Assumptions'!B12 | C8: ='01_Assumptions'!C12 | D8: ='01_Assumptions'!D12*(1+'01_Assumptions'!C18) | E8: ='01_Assumptions'!E12*(1+'01_Assumptions'!C19) | F8: ='01_Assumptions'!F12 | G8: =D8-E8-F8 | H8: =IF(D8=0,0,G8/D8) | I8: =H8-'01_Assumptions'!C20 | J8: =IF(H8>='01_Assumptions'!C20,"Green",IF(H8>='01_Assumptions'!C20-0.05,"Amber","Red")) | K8: ='01_Assumptions'!H12 | L8: =G8*K8 | M8: ='01_Assumptions'!G12 | N8: =L8-M8
B9: ='01_Assumptions'!B13 | C9: ='01_Assumptions'!C13 | D9: ='01_Assumptions'!D13*(1+'01_Assumptions'!C18) | E9: ='01_Assumptions'!E13*(1+'01_Assumptions'!C19) | F9: ='01_Assumptions'!F13 | G9: =D9-E9-F9 | H9: =IF(D9=0,0,G9/D9) | I9: =H9-'01_Assumptions'!C20 | J9: =IF(H9>='01_Assumptions'!C20,"Green",IF(H9>='01_Assumptions'!C20-0.05,"Amber","Red")) | K9: ='01_Assumptions'!H13 | L9: =G9*K9 | M9: ='01_Assumptions'!G13 | N9: =L9-M9
B10: ='01_Assumptions'!B14 | C10: ='01_Assumptions'!C14 | D10: ='01_Assumptions'!D14*(1+'01_Assumptions'!C18) | E10: ='01_Assumptions'!E14*(1+'01_Assumptions'!C19) | F10: ='01_Assumptions'!F14 | G10: =D10-E10-F10 | H10: =IF(D10=0,0,G10/D10) | I10: =H10-'01_Assumptions'!C20 | J10: =IF(H10>='01_Assumptions'!C20,"Green",IF(H10>='01_Assumptions'!C20-0.05,"Amber","Red")) | K10: ='01_Assumptions'!H14 | L10: =G10*K10 | M10: ='01_Assumptions'!G14 | N10: =L10-M10
B11: ='01_Assumptions'!B15 | C11: ='01_Assumptions'!C15 | D11: ='01_Assumptions'!D15*(1+'01_Assumptions'!C18) | E11: ='01_Assumptions'!E15*(1+'01_Assumptions'!C19) | F11: ='01_Assumptions'!F15 | G11: =D11-E11-F11 | H11: =IF(D11=0,0,G11/D11) | I11: =H11-'01_Assumptions'!C20 | J11: =IF(H11>='01_Assumptions'!C20,"Green",IF(H11>='01_Assumptions'!C20-0.05,"Amber","Red")) | K11: ='01_Assumptions'!H15 | L11: =G11*K11 | M11: ='01_Assumptions'!G15 | N11: =L11-M11
B13: TOTAL / avg | H13: =IF(SUMPRODUCT(D6:D11,K6:K11)=0,0,SUMPRODUCT(G6:G11,K6:K11)/SUMPRODUCT(D6:D11,K6:K11)) | K13: =SUM(K6:K11) | L13: =SUM(L6:L11) | M13: =SUM(M6:M11) | N13: =SUM(N6:N11)
B15: Unit contrib $ = Price − COGS − Var sell (after stress toggles). Ann contrib $000 = unit $ × volume (000).

Sheet 03_Channel_View
B2: 03 · Channel View
B3: Mix % by SKU (yellow) and channel fee % of price (yellow). Contribution after channel fee.
B5: Channel fee % of price (retailer / platform take)
B6: Metric | C6: Grocery | D6: Club | E6: eComm | F6: Convenience
B7: Fee % of price | C7: 0.28 | D7: 0.22 | E7: 0.18 | F7: 0.32
B9: Channel mix by SKU (must sum to ~100%)
B10: SKU | C10: Grocery | D10: Club | E10: eComm | F10: Convenience | G10: Mix check | H10: Unit CM $ (pre-fee) | I10: Blended fee % | J10: Unit CM $ after fee | K10: Ann CM $000
B11: ='01_Assumptions'!B10 | C11: 0.45 | D11: 0.25 | E11: 0.15 | F11: 0.15 | G11: =C11+D11+E11+F11 | H11: ='02_Unit_P&L'!G6 | I11: =C11*$C$7+D11*$D$7+E11*$E$7+F11*$F$7 | J11: =H11-'02_Unit_P&L'!D6*I11 | K11: =J11*'02_Unit_P&L'!K6
B12: ='01_Assumptions'!B11 | C12: 0.35 | D12: 0.35 | E12: 0.2 | F12: 0.1 | G12: =C12+D12+E12+F12 | H12: ='02_Unit_P&L'!G7 | I12: =C12*$C$7+D12*$D$7+E12*$E$7+F12*$F$7 | J12: =H12-'02_Unit_P&L'!D7*I12 | K12: =J12*'02_Unit_P&L'!K7
B13: ='01_Assumptions'!B12 | C13: 0.5 | D13: 0.15 | E13: 0.25 | F13: 0.1 | G13: =C13+D13+E13+F13 | H13: ='02_Unit_P&L'!G8 | I13: =C13*$C$7+D13*$D$7+E13*$E$7+F13*$F$7 | J13: =H13-'02_Unit_P&L'!D8*I13 | K13: =J13*'02_Unit_P&L'!K8
B14: ='01_Assumptions'!B13 | C14: 0.4 | D14: 0.3 | E14: 0.1 | F14: 0.2 | G14: =C14+D14+E14+F14 | H14: ='02_Unit_P&L'!G9 | I14: =C14*$C$7+D14*$D$7+E14*$E$7+F14*$F$7 | J14: =H14-'02_Unit_P&L'!D9*I14 | K14: =J14*'02_Unit_P&L'!K9
B15: ='01_Assumptions'!B14 | C15: 0.3 | D15: 0.2 | E15: 0.4 | F15: 0.1 | G15: =C15+D15+E15+F15 | H15: ='02_Unit_P&L'!G10 | I15: =C15*$C$7+D15*$D$7+E15*$E$7+F15*$F$7 | J15: =H15-'02_Unit_P&L'!D10*I15 | K15: =J15*'02_Unit_P&L'!K10
B16: ='01_Assumptions'!B15 | C16: 0.25 | D16: 0.2 | E16: 0.15 | F16: 0.4 | G16: =C16+D16+E16+F16 | H16: ='02_Unit_P&L'!G11 | I16: =C16*$C$7+D16*$D$7+E16*$E$7+F16*$F$7 | J16: =H16-'02_Unit_P&L'!D11*I16 | K16: =J16*'02_Unit_P&L'!K11
B18: Channel contribution $000s (volume × mix × unit CM after fee)
B19: SKU | C19: Grocery | D19: Club | E19: eComm | F19: Convenience | G19: Total
B20: =B11 | C20: ='02_Unit_P&L'!K6*C11*$J11 | D20: ='02_Unit_P&L'!K6*D11*$J11 | E20: ='02_Unit_P&L'!K6*E11*$J11 | F20: ='02_Unit_P&L'!K6*F11*$J11 | G20: =C20+D20+E20+F20
B21: =B12 | C21: ='02_Unit_P&L'!K7*C12*$J12 | D21: ='02_Unit_P&L'!K7*D12*$J12 | E21: ='02_Unit_P&L'!K7*E12*$J12 | F21: ='02_Unit_P&L'!K7*F12*$J12 | G21: =C21+D21+E21+F21
B22: =B13 | C22: ='02_Unit_P&L'!K8*C13*$J13 | D22: ='02_Unit_P&L'!K8*D13*$J13 | E22: ='02_Unit_P&L'!K8*E13*$J13 | F22: ='02_Unit_P&L'!K8*F13*$J13 | G22: =C22+D22+E22+F22
B23: =B14 | C23: ='02_Unit_P&L'!K9*C14*$J14 | D23: ='02_Unit_P&L'!K9*D14*$J14 | E23: ='02_Unit_P&L'!K9*E14*$J14 | F23: ='02_Unit_P&L'!K9*F14*$J14 | G23: =C23+D23+E23+F23
B24: =B15 | C24: ='02_Unit_P&L'!K10*C15*$J15 | D24: ='02_Unit_P&L'!K10*D15*$J15 | E24: ='02_Unit_P&L'!K10*E15*$J15 | F24: ='02_Unit_P&L'!K10*F15*$J15 | G24: =C24+D24+E24+F24
B25: =B16 | C25: ='02_Unit_P&L'!K11*C16*$J16 | D25: ='02_Unit_P&L'!K11*D16*$J16 | E25: ='02_Unit_P&L'!K11*E16*$J16 | F25: ='02_Unit_P&L'!K11*F16*$J16 | G25: =C25+D25+E25+F25
B27: TOTAL | C27: =SUM(C20:C25) | D27: =SUM(D20:D25) | E27: =SUM(E20:E25) | F27: =SUM(F20:F25) | G27: =SUM(G20:G25)
B29: Mix check should be ~100%. If not, channel $000s are still proportional but flag for cleanup.

Sheet 04_Cohort_or_Ramp
B2: 04 · Cohort / Ramp — NL-PROBIO launch
B3: 12-month volume ramp and cumulative contribution vs launch spend (slotting + CAC). Payback month highlighted.
B5: Launch SKU | C5: NL-PROBIO
B6: Unit price $ (linked) | C6: ='02_Unit_P&L'!D10
B7: Unit contrib $ (pre-fee) | C7: ='02_Unit_P&L'!G10
B8: Blended fee % (from channel) | C8: ='03_Channel_View'!I15
B9: Unit CM $ after fee | C9: =C7-C6*C8
B10: Payback hurdle (mo) | C10: ='01_Assumptions'!C21
B12: Metric | C12: M1 | D12: M2 | E12: M3 | F12: M4 | G12: M5 | H12: M6 | I12: M7 | J12: M8 | K12: M9 | L12: M10 | M12: M11 | N12: M12 | O12: FY Total
B13: Volume (000 units) | C13: 20 | D13: 35 | E13: 55 | F13: 70 | G13: 80 | H13: 90 | I13: 95 | J13: 100 | K13: 105 | L13: 110 | M13: 115 | N13: 125 | O13: =SUM(C13:N13)
B14: Launch spend $000s | C14: 120 | D14: 40 | E14: 25 | F14: 15 | G14: 10 | H14: 5 | I14: 5 | J14: 0 | K14: 0 | L14: 0 | M14: 0 | N14: 0 | O14: =SUM(C14:N14)
B15: Revenue $000s | C15: =$C$6*C13 | D15: =$C$6*D13 | E15: =$C$6*E13 | F15: =$C$6*F13 | G15: =$C$6*G13 | H15: =$C$6*H13 | I15: =$C$6*I13 | J15: =$C$6*J13 | ... N15: =$C$6*N13 | O15: =SUM(C15:N15)
B16: Contribution $000s | C16: =$C$9*C13 | D16: =$C$9*D13 | E16: =$C$9*E13 | F16: =$C$9*F13 | G16: =$C$9*G13 | H16: =$C$9*H13 | I16: =$C$9*I13 | J16: =$C$9*J13 | ... N16: =$C$9*N13 | O16: =SUM(C16:N16)
B17: Net of launch spend $000s | C17: =C16-C14 | D17: =D16-D14 | E17: =E16-E14 | F17: =F16-F14 | G17: =G16-G14 | H17: =H16-H14 | I17: =I16-I14 | J17: =J16-J14 | ... N17: =N16-N14 | O17: =SUM(C17:N17)
B18: Cumulative net $000s | C18: =C17 | D18: =C18+D17 | E18: =D18+E17 | F18: =E18+F17 | G18: =F18+G17 | H18: =G18+H17 | I18: =H18+I17 | J18: =I18+J17 | K18: =J18+K17 | ... N18: =M18+N17 | O18: =N18
B19: Payback reached? | C19: =IF(C18>=0,"YES","") | D19: =IF(AND(C18<0,D18>=0),"YES",IF(D18>=0,"","")) | E19: =IF(AND(D18<0,E18>=0),"YES",IF(E18>=0,"","")) | F19: =IF(AND(E18<0,F18>=0),"YES",IF(F18>=0,"","")) | G19: =IF(AND(F18<0,G18>=0),"YES",IF(G18>=0,"","")) | H19: =IF(AND(G18<0,H18>=0),"YES",IF(H18>=0,"","")) | I19: =IF(AND(H18<0,I18>=0),"YES",IF(I18>=0,"","")) | J19: =IF(AND(I18<0,J18>=0),"YES",IF(J18>=0,"","")) | K19: =IF(AND(J18<0,K18>=0),"YES",IF(K18>=0,"","")) | ... N19: =IF(AND(M18<0,N18>=0),"YES",IF(N18>=0,"",""))
B21: Payback month # | C21: =IFERROR(MATCH("YES",C19:N19,0),"Not within 12 mo")
B22: Within hurdle? | C22: =IF(ISNUMBER(C21),IF(C21<=C10,"Yes — inside hurdle","No — beyond hurdle"),"No — not paid back")
B23: Year-1 CM after launch spend $000s | C23: =O17
B25: Edit yellow volume and launch spend to stress payback. Unit CM flows from Assumptions → Unit P&L → Channel fees.

Sheet 05_Dashboard
B1: ="NORTHLINE · UNIT ECONOMICS DASHBOARD · "&'01_Assumptions'!C6
B2: ='01_Assumptions'!C5&" · per-unit $ and $000s · fictional sample"
B4: PORTFOLIO CM % | D4: ANN CONTRIB $000 | F4: AFTER SLOTTING | I4: LAUNCH PAYBACK MO | K4: Y1 NET $000
B5: ='02_Unit_P&L'!H13 | D5: ='02_Unit_P&L'!L13 | F5: ='02_Unit_P&L'!N13 | I5: ='04_Cohort_or_Ramp'!C21 | K5: ='04_Cohort_or_Ramp'!C23
B7: SKU CONTRIBUTION RANK | I7: LAUNCH SNAPSHOT (NL-PROBIO)
B8: SKU | C8: CM % | D8: RAG | E8: Ann CM $000 | F8: After slot $000 | I8: Unit CM $ after fee | J8: ='04_Cohort_or_Ramp'!C9
B9: ='02_Unit_P&L'!B6 | C9: ='02_Unit_P&L'!H6 | D9: ='02_Unit_P&L'!J6 | E9: ='02_Unit_P&L'!L6 | F9: ='02_Unit_P&L'!N6 | I9: FY volume (000) | J9: ='04_Cohort_or_Ramp'!O13
B10: ='02_Unit_P&L'!B7 | C10: ='02_Unit_P&L'!H7 | D10: ='02_Unit_P&L'!J7 | E10: ='02_Unit_P&L'!L7 | F10: ='02_Unit_P&L'!N7 | I10: FY contribution $000 | J10: ='04_Cohort_or_Ramp'!O16
B11: ='02_Unit_P&L'!B8 | C11: ='02_Unit_P&L'!H8 | D11: ='02_Unit_P&L'!J8 | E11: ='02_Unit_P&L'!L8 | F11: ='02_Unit_P&L'!N8 | I11: Launch spend $000 | J11: ='04_Cohort_or_Ramp'!O14
B12: ='02_Unit_P&L'!B9 | C12: ='02_Unit_P&L'!H9 | D12: ='02_Unit_P&L'!J9 | E12: ='02_Unit_P&L'!L9 | F12: ='02_Unit_P&L'!N9 | I12: Y1 net $000 | J12: ='04_Cohort_or_Ramp'!C23
B13: ='02_Unit_P&L'!B10 | C13: ='02_Unit_P&L'!H10 | D13: ='02_Unit_P&L'!J10 | E13: ='02_Unit_P&L'!L10 | F13: ='02_Unit_P&L'!N10 | I13: Payback month | J13: ='04_Cohort_or_Ramp'!C21
B14: ='02_Unit_P&L'!B11 | C14: ='02_Unit_P&L'!H11 | D14: ='02_Unit_P&L'!J11 | E14: ='02_Unit_P&L'!L11 | F14: ='02_Unit_P&L'!N11 | I14: Within hurdle? | J14: ='04_Cohort_or_Ramp'!C22
B16: CHANNEL TOTALS ($000s) | I16: STRESS TOGGLES (from Assumptions)
B17: Grocery | C17: Club | D17: eComm | E17: Convenience | F17: Total | I17: Price stress % | J17: ='01_Assumptions'!C18
B18: ='03_Channel_View'!C27 | C18: ='03_Channel_View'!D27 | D18: ='03_Channel_View'!E27 | E18: ='03_Channel_View'!F27 | F18: ='03_Channel_View'!G27 | I18: COGS stress % | J18: ='01_Assumptions'!C19
I19: Target CM % | J19: ='01_Assumptions'!C20
B20: Chart data
B21: SKU | C21: Ann CM $000
B22: ='02_Unit_P&L'!B6 | C22: ='02_Unit_P&L'!L6
B23: ='02_Unit_P&L'!B7 | C23: ='02_Unit_P&L'!L7
B24: ='02_Unit_P&L'!B8 | C24: ='02_Unit_P&L'!L8
B25: ='02_Unit_P&L'!B9 | C25: ='02_Unit_P&L'!L9
B26: ='02_Unit_P&L'!B10 | C26: ='02_Unit_P&L'!L10
B27: ='02_Unit_P&L'!B11 | C27: ='02_Unit_P&L'!L11
B28: Edit Assumptions (yellow) → Unit P&L / Channel / Ramp recalculate → this dashboard updates · fictional sample

Sheet 06_Data_Dictionary
B2: 06 · Data Dictionary
B3: Field definitions so another analyst can inherit the file.
B5: Field | C5: Tab | D5: Definition
B6: SKU / Product | C6: 01_Assumptions | D6: Fictional Northline assortment codes and names.
B7: Price $ | C7: 01_Assumptions | D7: List / shelf price per unit before channel fees.
B8: COGS $ | C8: 01_Assumptions | D8: Variable product cost per unit.
B9: Var sell $ | C9: 01_Assumptions | D9: Variable selling cost per unit (freight-out, broker, etc.).
B10: Slotting $000 | C10: 01_Assumptions | D10: Annualized slotting / listing fees in $000s. Launch SKU also has monthly CAC on the ramp tab.
B11: Ann vol (000) | C11: 01_Assumptions | D11: Annual volume in thousands of units.
B12: Price / COGS stress % | C12: 01_Assumptions | D12: Global toggles applied on Unit P&L to sensitivity-test margin.
B13: Target CM % | C13: 01_Assumptions | D13: Hurdle contribution margin for RAG.
B14: Unit contrib $ | C14: 02_Unit_P&L | D14: Price − COGS − Var sell (after stress). Key output.
B15: CM % | C15: 02_Unit_P&L | D15: Unit contrib ÷ Price.
B16: Ann contrib $000 | C16: 02_Unit_P&L | D16: Unit contrib $ × annual volume (000).
... B27: Units | C27: All | D27: Per-unit in $. Annual flows in $000s. Volume in 000 units.
B29: All sample numbers are fictional. Built for a public GitHub portfolio — no employer data.
